README.md
setup.py
mvtb_images.egg-info/PKG-INFO
mvtb_images.egg-info/SOURCES.txt
mvtb_images.egg-info/dependency_links.txt
mvtb_images.egg-info/top_level.txt
mvtbimages/58060.png
mvtbimages/5points.png
mvtbimages/Image18.png
mvtbimages/__init__.py
mvtbimages/adelson.png
mvtbimages/apriltag12.png
mvtbimages/bouget.mat
mvtbimages/building2-1.png
mvtbimages/building2-2.png
mvtbimages/building2-3.png
mvtbimages/butterfly.jpg
mvtbimages/castle.png
mvtbimages/castle2.png
mvtbimages/church.png
mvtbimages/edgeblobs.png
mvtbimages/eiffel2-1.png
mvtbimages/eiffel2-2.png
mvtbimages/fisheye_target.png
mvtbimages/flowers1.png
mvtbimages/flowers2.png
mvtbimages/flowers3.png
mvtbimages/flowers4.png
mvtbimages/flowers5.png
mvtbimages/flowers6.png
mvtbimages/flowers7.png
mvtbimages/flowers8.png
mvtbimages/flowers9.png
mvtbimages/greenscreen.png
mvtbimages/lena.png
mvtbimages/monalisa.png
mvtbimages/multiblobs.png
mvtbimages/notre-dame.png
mvtbimages/parks.png
mvtbimages/penguins.png
mvtbimages/road.png
mvtbimages/rocks2-l.png
mvtbimages/rocks2-r.png
mvtbimages/roof.png
mvtbimages/scale-space.png
mvtbimages/segmentation.png
mvtbimages/shark1.png
mvtbimages/shark2.png
mvtbimages/shark2a.png
mvtbimages/sharks.png
mvtbimages/street.png
mvtbimages/tomato_124.png
mvtbimages/tomato_14.png
mvtbimages/tomato_35.png
mvtbimages/tomato_54.png
mvtbimages/traffic_sequence.mpg
mvtbimages/walls-l.png
mvtbimages/walls-r.png
mvtbimages/wally.png
mvtbimages/wheres-wally.png
mvtbimages/yellowtargets.png
mvtbimages/__pycache__/__init__.cpython-38.pyc
mvtbimages/seq/im.001.png
mvtbimages/seq/im.002.png
mvtbimages/seq/im.003.png
mvtbimages/seq/im.004.png
mvtbimages/seq/im.005.png
mvtbimages/seq/im.006.png
mvtbimages/seq/im.007.png
mvtbimages/seq/im.008.png
mvtbimages/seq/im.009.png