Metadata-Version: 2.1
Name: mvtb-images
Version: 1.1
Summary: Images for the Machine Vision Toolbox for Python.
Home-page: https://github.com/petercorke/machinevision-toolbox-python
Author: Peter Corke
Author-email: rvc@petercorke.com
License: UNKNOWN
Project-URL: Source, https://github.com/petercorke/machinevision-toolbox-python
Keywords: python machine-vision computer-vision color blobs
Platform: UNKNOWN
Classifier: Development Status :: 5 - Production/Stable
Classifier: Intended Audience :: Developers
Classifier: License :: OSI Approved :: MIT License
Classifier: Programming Language :: Python :: 3 :: Only
